{"chunk_definitions":[{"row":19,"row_count":1,"visible":true,"expansion_state":0,"options":{"include":false,"engine":"r","label":"unnamed-chunk-2"},"document_id":"D7908B5F","chunk_id":"c22k93olspdcj","chunk_label":"unnamed-chunk-1"},{"row":38,"row_count":1,"visible":true,"expansion_state":0,"options":{"include":false,"engine":"r","label":"unnamed-chunk-3"},"document_id":"D7908B5F","chunk_id":"cgmablmo9tsnx","chunk_label":"unnamed-chunk-2"},{"row":57,"row_count":1,"visible":true,"expansion_state":0,"options":{"include":false,"engine":"r","label":"unnamed-chunk-4"},"document_id":"D7908B5F","chunk_id":"cdj0eqos27uas","chunk_label":"unnamed-chunk-3"},{"row":66,"row_count":1,"visible":true,"expansion_state":0,"options":{"include":false,"engine":"r","label":"unnamed-chunk-5"},"document_id":"D7908B5F","chunk_id":"c052hde9d6fh3","chunk_label":"unnamed-chunk-4"}],"doc_write_time":1682716164}